{"data_mtime": 1668782398, "dep_lines": [1, 20, 2, 10, 1, 1, 1], "dep_prios": [5, 5, 5, 5, 5, 20, 30], "dependencies": ["collections.abc", "numpy._typing", "typing", "numpy", "builtins", "wandb.proto.wandb_base_pb2", "abc"], "hash": "2cfbc0bc8c54fa9e62fd07be89cee112fa383937d2acda69971306ece0197bc4", "id": "numpy.lib.type_check", "ignore_all": true, "interface_hash": "c03689a73e3d6eb60050f9c605ddfa55f860b82a8c52c5d6fa65440c07867bf9", "mtime": 1668770024, "options": {"allow_redefinition": false, "allow_untyped_globals": false, "always_false": [], "always_true": [], "bazel": false, "check_untyped_defs": false, "disable_error_code": [], "disabled_error_codes": [], "disallow_any_decorated": false, "disallow_any_explicit": false, "disallow_any_expr": false, "disallow_any_generics": false, "disallow_any_unimported": false, "disallow_incomplete_defs": false, "disallow_subclassing_any": false, "disallow_untyped_calls": false, "disallow_untyped_decorators": false, "disallow_untyped_defs": false, "enable_error_code": [], "enabled_error_codes": [], "follow_imports": "silent", "follow_imports_for_stubs": false, "ignore_errors": false, "ignore_missing_imports": true, "implicit_reexport": true, "local_partial_types": false, "mypyc": false, "no_implicit_optional": false, "platform": "linux", "plugins": [], "show_none_errors": true, "strict_concatenate": false, "strict_equality": false, "strict_optional": true, "strict_optional_whitelist": null, "warn_no_return": true, "warn_return_any": false, "warn_unreachable": false, "warn_unused_ignores": false}, "path": "/root/hiddeninfo/.env/lib/python3.8/site-packages/numpy/lib/type_check.pyi", "plugin_data": null, "size": 5571, "suppressed": [], "version_id": "0.981"}